twsemcp/__init__.py
twsemcp/py.typed
twsemcp/server.py
twsemcp-0.1.3.dist-info/METADATA
twsemcp-0.1.3.dist-info/WHEEL
twsemcp-0.1.3.dist-info/entry_points.txt
twsemcp-0.1.3.dist-info/licenses/LICENSE
twsemcp-0.1.3.dist-info/RECORD
