Metadata-Version: 2.4
Name: twsemcp
Version: 0.1.3
Author-email: narumi <toucans-cutouts0f@icloud.com>
License-File: LICENSE
Requires-Python: >=3.12
Requires-Dist: loguru>=0.7.3
Requires-Dist: mcp>=1.6.0
Requires-Dist: twse>=0.4.0
